qimage_hwc_bgrx_8888_ndarray_interop.py
qimage_hwc_bgrx_8888_ndarray_interop-0.1.0a0.dist-info/licenses/LICENSE
qimage_hwc_bgrx_8888_ndarray_interop-0.1.0a0.dist-info/METADATA
qimage_hwc_bgrx_8888_ndarray_interop-0.1.0a0.dist-info/WHEEL
qimage_hwc_bgrx_8888_ndarray_interop-0.1.0a0.dist-info/top_level.txt
qimage_hwc_bgrx_8888_ndarray_interop-0.1.0a0.dist-info/RECORD
