Metadata-Version: 2.4
Name: qimage-hwc-bgrx-8888-ndarray-interop
Version: 0.1.0a0
Summary: Zero-copy conversion between Qt QImage (in `Format_RGB32`/`Format_ARGB32`) and NumPy ndarray (in HWC BGRX 8888 format).
Author-email: Jifeng Wu <jifengwu2k@gmail.com>
License-Expression: MIT
Project-URL: Homepage, https://github.com/jifengwu2k/qimage-hwc-bgrx-8888-ndarray-interop
Project-URL: Bug Tracker, https://github.com/jifengwu2k/qimage-hwc-bgrx-8888-ndarray-interop/issues
Classifier: Programming Language :: Python :: 2
Classifier: Programming Language :: Python :: 3
Classifier: Operating System :: OS Independent
Requires-Python: >=2
License-File: LICENSE
Requires-Dist: detect-qt-binding
Requires-Dist: numpy
Dynamic: license-file
